TSHIELD/__init__.py
TSHIELD/TSHIELD/__init__.py
TSHIELD/TSHIELD/tshield.py
TSHIELD/procedures/__init__.py
TSHIELD/procedures/procedures.py
TSHIELD/tests/REVEL_metrics.py
TSHIELD/tests/__init__.py
TSHIELD/tests/parser.py
TSHIELD/tests/test.py
TSHIELD/tests/train.py
tshield_xai-0.0.1.dist-info/LICENSE
tshield_xai-0.0.1.dist-info/METADATA
tshield_xai-0.0.1.dist-info/WHEEL
tshield_xai-0.0.1.dist-info/top_level.txt
tshield_xai-0.0.1.dist-info/RECORD
