Metadata-Version: 2.1
Name: tshield-xai
Version: 0.0.1
Summary: T-SHIELD Regularization for Artificial Intelligence
Author: Iván Sevillano Garcia
Author-email: Ivan Sevillano-Garcia <isevillano@ugr.es>
Project-URL: Homepage, https://github.com/isega24/SHIELD
Classifier: Programming Language :: Python :: 3
Classifier: License :: OSI Approved :: MIT License
Classifier: Operating System :: OS Independent
Requires-Python: >=3.8
License-File: LICENSE
Requires-Dist: torch
Requires-Dist: scikit-learn
Requires-Dist: scikit-image
Requires-Dist: matplotlib
Requires-Dist: numpy
Requires-Dist: scipy
Requires-Dist: pandas
Requires-Dist: torchvision
Requires-Dist: efficientnet-pytorch
Requires-Dist: tqdm
Requires-Dist: opencv-python
Requires-Dist: IPython
Requires-Dist: seaborn
Requires-Dist: plotly
Requires-Dist: ipywidgets
Requires-Dist: sphinx
Requires-Dist: sphinx-rtd-theme
Requires-Dist: sphinxcontrib.bibtex
Requires-Dist: nbsphinx
Requires-Dist: wget
Requires-Dist: pandoc
Requires-Dist: revel-xai
Requires-Dist: torchsummary
Requires-Dist: tensorboard
Requires-Dist: twine
